cmc/__init__.py
cmc/coinmarketcap.py
cmc/async/__init__.py
cmc/async/async_utils.py
cmc/utils/__init__.py
cmc/utils/utils.py
cmctestingthree-0.0.1.data/scripts/coinmarketcap
cmctestingthree-0.0.1.dist-info/METADATA
cmctestingthree-0.0.1.dist-info/RECORD
cmctestingthree-0.0.1.dist-info/WHEEL
cmctestingthree-0.0.1.dist-info/top_level.txt
