Metadata-Version: 2.1
Name: cmctestingthree
Version: 0.0.1
Summary: Get the price history for CoinMarketCap-listed currencies
Home-page: https://github.com/Alescontrela/coinmarketcap-history
Author: Alejandro Escontrela,James Hogan
Author-email: alejandroescontrela@gmail.com
License: UNKNOWN
Platform: UNKNOWN
Classifier: Programming Language :: Python :: 3
Classifier: License :: OSI Approved :: MIT License
Classifier: Operating System :: OS Independent
